odoo/addons/storage_import_image_advanced/README.rst
odoo/addons/storage_import_image_advanced/__init__.py
odoo/addons/storage_import_image_advanced/__manifest__.py
odoo/addons/storage_import_image_advanced/data/ir_cron.xml
odoo/addons/storage_import_image_advanced/data/queue_job_channel_data.xml
odoo/addons/storage_import_image_advanced/data/queue_job_function_data.xml
odoo/addons/storage_import_image_advanced/i18n/shopinvader_import_image.pot
odoo/addons/storage_import_image_advanced/i18n/storage_import_image_advanced.pot
odoo/addons/storage_import_image_advanced/models/__init__.py
odoo/addons/storage_import_image_advanced/models/import_image.py
odoo/addons/storage_import_image_advanced/readme/CONTRIBUTORS.rst
odoo/addons/storage_import_image_advanced/readme/DESCRIPTION.rst
odoo/addons/storage_import_image_advanced/security/ir_model_access.xml
odoo/addons/storage_import_image_advanced/static/description/icon.png
odoo/addons/storage_import_image_advanced/static/description/index.html
odoo/addons/storage_import_image_advanced/tests/__init__.py
odoo/addons/storage_import_image_advanced/tests/test_import_image.py
odoo/addons/storage_import_image_advanced/tests/fixture/A001.jpg
odoo/addons/storage_import_image_advanced/tests/fixture/A002.jpg
odoo/addons/storage_import_image_advanced/tests/fixture/A003.jpg
odoo/addons/storage_import_image_advanced/tests/fixture/image_import_test.csv
odoo/addons/storage_import_image_advanced/tests/fixture/image_import_test.zip
odoo/addons/storage_import_image_advanced/tests/fixture/image_import_test_1.csv
odoo/addons/storage_import_image_advanced/views/import_product_image_view.xml
odoo/addons/storage_import_image_advanced/views/report_html.xml
odoo14_addon_storage_import_image_advanced-14.0.1.0.4.dist-info/METADATA
odoo14_addon_storage_import_image_advanced-14.0.1.0.4.dist-info/WHEEL
odoo14_addon_storage_import_image_advanced-14.0.1.0.4.dist-info/top_level.txt
odoo14_addon_storage_import_image_advanced-14.0.1.0.4.dist-info/RECORD
