Metadata-Version: 2.1
Name: odoo14-addon-storage-import-image-advanced
Version: 14.0.1.0.4
Summary: Import product images using CSV
Home-page: https://github.com/OCA/storage
Author: Akretion, Camptocamp, Odoo Community Association (OCA)
Author-email: support@odoo-community.org
License: AGPL-3
Platform: UNKNOWN
Classifier: Programming Language :: Python
Classifier: Framework :: Odoo
Classifier: Framework :: Odoo :: 14.0
Classifier: License :: OSI Approved :: GNU Affero General Public License v3
Requires-Python: >=3.6
Requires-Dist: odoo14-addon-queue-job
Requires-Dist: odoo14-addon-storage-image-product
Requires-Dist: odoo <14.1dev,>=14.0a
Requires-Dist: python-magic
Requires-Dist: validators
